maas_env/__init__.py
maas_env/config.yaml
maas_env/maas_env.py
maas_dev_env-0.0.1.dist-info/METADATA
maas_dev_env-0.0.1.dist-info/WHEEL
maas_dev_env-0.0.1.dist-info/entry_points.txt
maas_dev_env-0.0.1.dist-info/top_level.txt
maas_dev_env-0.0.1.dist-info/RECORD
