Metadata-Version: 2.4
Name: maas-dev-env
Version: 0.0.1
Summary: Utility to manage MAAS dev env
Author-email: Alessandro Marcolini <alessandromarcolini99@gmail.com>
Requires-Python: >=3.12
Requires-Dist: pyyaml
